flavpy/__init__.py
flavpy/capture/__init__.py
flavpy/capture/_capture.py
flavpy/inspector/__init__.py
flavpy/inspector/inspector.py
flavpy/writer/__init__.py
flavpy/writer/_writer.py
flavpy-1.0.2.dist-info/METADATA
flavpy-1.0.2.dist-info/WHEEL
flavpy-1.0.2.dist-info/top_level.txt
flavpy-1.0.2.dist-info/RECORD
