Metadata-Version: 2.1
Name: flavpy
Version: 1.0.2
Summary: 味覚情報を埋め込み可能なファイル形式:FlavMP4のキャプチャ、書き出しを行う
Home-page: https://github.com/hmwri/flavtool
Author: Taiyu Honma
Author-email: ev220526@meiji.ac.jp
Classifier: Programming Language :: Python :: 3.7
Classifier: License :: OSI Approved :: MIT License
Classifier: Operating System :: OS Independent
Requires-Dist: flavtool
Requires-Dist: coloredlogs
Requires-Dist: opencv-python
Requires-Dist: numpy
